{
    "backend": "api-server-flask",
    "db_name": "",
    "db_pass": "",
    "db_type": "sqlite",
    "db_user": "",
    "dbms": "1",
    "description": "generated product",
    "design": "material-kit",
    "docker": "0",
    "err_code": 0,
    "frontend": "react",
    "heroku": "0",
    "pattern": "fullstack",
    "pro": "0",
    "task_id": "882e2ccf-0417-44a2-b30e-ab33b20260de",
    "task_info": "Upload Sources [0%] - 312 files",
    "task_output": "882e2ccf-0417-44a2-b30e-ab33b20260de.zip",
    "task_result": "SUCCESS",
    "task_state": "RUNNING",
    "task_ts_end": "2023-07-19-05-48-04",
    "task_ts_start": "2023-07-19-05-48-02"
}